Lab 2/P2/one_bit_4to1muxV2.v
module one_bit_4to1muxV2 (s,u,v,w,x,m);
 
	input[1:0] s;
	input u,v,w,x;
	output reg m;
	
	reg t1, t2;
	
	always @(u,v,s[0]) begin
		if (s[0] == 1'b0) begin
			t1 = u;
			t2 = w;
		end else begin
			t1 = v;
			t2 = x;
		end
	end
 
	always @(t1,t2,s[1]) begin
		if (s[1] == 1'b0)
			m = t1;
		else
			m = t2;
	end


endmodule

Lab 2/P3/two_bit_4to1mux.v
module two_bit_4to1mux (s,u,v,w,x,m);
 
	input[1:0] s;
	input[1:0] u, v, w, x;
	output[1:0] m;
	
	one_bit_4to1muxV2 mux1(.s(s),.u(u[0]),.v(v[0]),.w(w[0]),.x(x[0]),.m(m[0]));
	one_bit_4to1muxV2 mux2(.s(s),.u(u[1]),.v(v[1]),.w(w[1]),.x(x[1]),.m(m[1]));
endmodule

Lab 2/P3/part3_TB.v
`timescale 1ns / 1ps
 
module part3_TB;
 
	// ------------------ Instantiate module ------------------
	// We are instantiating the module mux2, naming it instantiate_mux2.
	// select, input1, input2 are controlled by the testbench, output is 
	// checked  within the testbench
 
	reg [3:0] count;
	reg [1:0] select;
	reg [1:0] input1, input2, input3, input4;
	wire [1:0] output1;
	
	two_bit_4to1mux instantiate_mux4_2bit(.s(select),.u(input1),.v(input2),.w(input3),.x(input4),.m(output1));
 	
	initial begin 
		count = 4'b0000;
	end
	
	always begin
		#50
		count=count+4'b0001;
	end
	
	always @(count) begin
		case (count)
		4'b0000 : begin input1 = 2'b01; input2 = 2'b00; input3 = 2'b00; input4 = 2'b00; select = 2'b00; end
		4'b0001 : begin input1 = 2'b01; input2 = 2'b00; input3 = 2'b00; input4 = 2'b00; select = 2'b01; end
		4'b0010 : begin input1 = 2'b01; input2 = 2'b00; input3 = 2'b00; input4 = 2'b00; select = 2'b10; end
		4'b0011 : begin input1 = 2'b01; input2 = 2'b00; input3 = 2'b00; input4 = 2'b00; select = 2'b11; end
		4'b0100 : begin input1 = 2'b00; input2 = 2'b01; input3 = 2'b00; input4 = 2'b00; select = 2'b00; end
		4'b0101 : begin input1 = 2'b00; input2 = 2'b01; input3 = 2'b00; input4 = 2'b00; select = 2'b01; end
		4'b0110 : begin input1 = 2'b00; input2 = 2'b01; input3 = 2'b00; input4 = 2'b00; select = 2'b10; end
		4'b0111 : begin input1 = 2'b00; input2 = 2'b01; input3 = 2'b00; input4 = 2'b00; select = 2'b11; end
		default : begin input1 = 2'b00; input2 = 2'b00; input3 = 2'b00; input4 = 2'b00; select = 2'b00; end
	endcase
	end

       // Terminate the simulation after a certain period
    initial begin
        // Initialize VCD dump
        $dumpfile("testbench.vcd");
        $dumpvars(0, part3_TB);
        
        #500 $finish;
    end

endmodule

Lab 2/P3/testbench.vcd
$date
	Thu Mar 20 13:24:00 2025
$end
$version
	Icarus Verilog
$end
$timescale
	1ps
$end
$scope module part3_TB $end
$var wire 2 ! output1 [1:0] $end
$var reg 4 " count [3:0] $end
$var reg 2 # input1 [1:0] $end
$var reg 2 $ input2 [1:0] $end
$var reg 2 % input3 [1:0] $end
$var reg 2 & input4 [1:0] $end
$var reg 2 ' select [1:0] $end
$scope module instantiate_mux4_2bit $end
$var wire 2 ( s [1:0] $end
$var wire 2 ) u [1:0] $end
$var wire 2 * v [1:0] $end
$var wire 2 + w [1:0] $end
$var wire 2 , x [1:0] $end
$var wire 2 - m [1:0] $end
$scope module mux1 $end
$var wire 2 . s [1:0] $end
$var wire 1 / u $end
$var wire 1 0 v $end
$var wire 1 1 w $end
$var wire 1 2 x $end
$var reg 1 3 m $end
$var reg 1 4 t1 $end
$var reg 1 5 t2 $end
$upscope $end
$scope module mux2 $end
$var wire 2 6 s [1:0] $end
$var wire 1 7 u $end
$var wire 1 8 v $end
$var wire 1 9 w $end
$var wire 1 : x $end
$var reg 1 ; m $end
$var reg 1 < t1 $end
$var reg 1 = t2 $end
$upscope $end
$upscope $end
$upscope $end
$enddefinitions $end
$comment Show the parameter values. $end
$dumpall
$end
#0
$dumpvars
0=
0<
0;
0:
09
08
07
b0 6
05
14
13
02
01
00
1/
b0 .
b1 -
b0 ,
b0 +
b0 *
b1 )
b0 (
b0 '
b0 &
b0 %
b0 $
b1 #
b0 "
b1 !
$end
#50000
b0 !
b0 -
03
04
b1 '
b1 (
b1 .
b1 6
b1 "
#100000
14
b10 '
b10 (
b10 .
b10 6
b10 "
#150000
04
b11 '
b11 (
b11 .
b11 6
b11 "
#200000
10
0/
b0 '
b0 (
b0 .
b0 6
b1 $
b1 *
b0 #
b0 )
b100 "
#250000
b1 !
b1 -
13
14
b1 '
b1 (
b1 .
b1 6
b101 "
#300000
04
b0 !
b0 -
03
b10 '
b10 (
b10 .
b10 6
b110 "
#350000
14
b11 '
b11 (
b11 .
b11 6
b111 "
#400000
04
00
b0 '
b0 (
b0 .
b0 6
b0 $
b0 *
b1000 "
#450000
b1001 "
#500000
b1010 "
