Lab 5/P2/counter.v
module counter (Clkin, clear, Din, Q);
    input Clkin, clear, Din;
    output reg [15:0] Q;

    always @(posedge Clkin or posedge clear) begin
        if (clear) begin
            Q <= 16'b0; // Reset the counter to 0
        end else if (Din) begin
            Q <= Q + 1; // Increment the counter
        end
    end
endmodule

Lab 5/P1/TB.v
`timescale 1ns / 1ps
 
module TB;
 
	// ------------------ Instantiate module ------------------
	// We are instantiating the module counter, and testing with the relevant signals
	
	reg [3:0] count;
    reg Din,Clkin,clear;
    wire [3:0] Q;
	
	// instantiate the counter

    counter instantiate_counter (Clkin, clear, Din, Q);
	
	initial begin 
		count = 4'b0000;
		Clkin =1'b0;
        clear = 1'b1; // Assert clear
        #50 clear = 1'b0; // Deassert clear after 50 time units
	end
	
	always begin
		#50
		count=count+4'b0001;
	end
	
	always begin
		#10
		Clkin = 1'b0;
		#10
		Clkin = 1'b1;
	end	

	
	always @(count) begin
		case (count)
		4'b0000 : begin Din = 1'b1; end
		4'b0001 : begin Din = 1'b1; end
		4'b0010 : begin Din = 1'b1; end
		4'b0011 : begin Din = 1'b1; end
		4'b0100 : begin Din = 1'b1; end
		4'b0101 : begin Din = 1'b1; end
		4'b0110 : begin Din = 1'b1; end
		4'b0111 : begin Din = 1'b1; end
		4'b1000 : begin Din = 1'b1; end
		4'b1001 : begin Din = 1'b0; end
		4'b1010 : begin Din = 1'b0; end
		4'b1011 : begin Din = 1'b0; end
		4'b1100 : begin Din = 1'b0; end
		4'b1101 : begin Din = 1'b0; end
		4'b1110 : begin Din = 1'b0; end
		4'b1111 : begin Din = 1'b0; end
		default : begin Din = 1'b0; end
	endcase
	end

      initial begin
        // Initialize VCD dump
        $dumpfile("TB.vcd");
        $dumpvars(0, TB);
        
        #1000 $finish;
    end
endmodule

Lab 5/P2/TB.vcd
$date
	Thu Apr 10 13:11:51 2025
$end
$version
	Icarus Verilog
$end
$timescale
	1ps
$end
$scope module TB $end
$var wire 4 ! Q [3:0] $end
$var reg 1 " Clkin $end
$var reg 1 # Din $end
$var reg 1 $ clear $end
$var reg 4 % count [3:0] $end
$scope module instantiate_counter $end
$var wire 1 " Clkin $end
$var wire 1 # Din $end
$var wire 1 $ clear $end
$var reg 16 & Q [15:0] $end
$upscope $end
$upscope $end
$enddefinitions $end
$comment Show the parameter values. $end
$dumpall
$end
#0
$dumpvars
b0 &
b0 %
1$
1#
0"
b0 !
$end
#20000
1"
#30000
0"
#40000
1"
#50000
0"
b1 %
0$
#60000
b1 !
b1 &
1"
#70000
0"
#80000
b10 !
b10 &
1"
#90000
0"
#100000
b11 !
b11 &
1"
b10 %
#110000
0"
#120000
b100 !
b100 &
1"
#130000
0"
#140000
b101 !
b101 &
1"
#150000
0"
b11 %
#160000
b110 !
b110 &
1"
#170000
0"
#180000
b111 !
b111 &
1"
#190000
0"
#200000
b1000 !
b1000 &
1"
b100 %
#210000
0"
#220000
b1001 !
b1001 &
1"
#230000
0"
#240000
b1010 !
b1010 &
1"
#250000
0"
b101 %
#260000
b1011 !
b1011 &
1"
#270000
0"
#280000
b1100 !
b1100 &
1"
#290000
0"
#300000
b1101 !
b1101 &
1"
b110 %
#310000
0"
#320000
b1110 !
b1110 &
1"
#330000
0"
#340000
b1111 !
b1111 &
1"
#350000
0"
b111 %
#360000
b0 !
b10000 &
1"
#370000
0"
#380000
b1 !
b10001 &
1"
#390000
0"
#400000
b10 !
b10010 &
1"
b1000 %
#410000
0"
#420000
b11 !
b10011 &
1"
#430000
0"
#440000
b100 !
b10100 &
1"
#450000
0#
0"
b1001 %
#460000
1"
#470000
0"
#480000
1"
#490000
0"
#500000
1"
b1010 %
#510000
0"
#520000
1"
#530000
0"
#540000
1"
#550000
0"
b1011 %
#560000
1"
#570000
0"
#580000
1"
#590000
0"
#600000
1"
b1100 %
#610000
0"
#620000
1"
#630000
0"
#640000
1"
#650000
0"
b1101 %
#660000
1"
#670000
0"
#680000
1"
#690000
0"
#700000
1"
b1110 %
#710000
0"
#720000
1"
#730000
0"
#740000
1"
#750000
0"
b1111 %
#760000
1"
#770000
0"
#780000
1"
#790000
0"
#800000
b101 !
b10101 &
1#
1"
b0 %
#810000
0"
#820000
b110 !
b10110 &
1"
#830000
0"
#840000
b111 !
b10111 &
1"
#850000
0"
b1 %
#860000
b1000 !
b11000 &
1"
#870000
0"
#880000
b1001 !
b11001 &
1"
#890000
0"
#900000
b1010 !
b11010 &
1"
b10 %
#910000
0"
#920000
b1011 !
b11011 &
1"
#930000
0"
#940000
b1100 !
b11100 &
1"
#950000
0"
b11 %
#960000
b1101 !
b11101 &
1"
#970000
0"
#980000
b1110 !
b11110 &
1"
#990000
0"
#1000000
b1111 !
b11111 &
1"
b100 %
