Lab 3/P2/lab3_p2_v2.v
module lab3_p2_v2 (v, d1, d2);
    input [3:0] v; 
	output reg[6:0] d1, d2; 
	
	always @(v) begin
		case (v)
		4'b0000 : begin d1 = 7'b0111111; d2 = 7'b0111111; end // 00
		4'b0001 : begin d1 = 7'b0111111; d2 = 7'b0000110; end // 01
		4'b0010 : begin d1 = 7'b0111111; d2 = 7'b1011011; end // 02
		4'b0011 : begin d1 = 7'b0111111; d2 = 7'b1001111; end // 03
		4'b0100 : begin d1 = 7'b0111111; d2 = 7'b1100110; end // 04
		4'b0101 : begin d1 = 7'b0111111; d2 = 7'b1101101; end // 05
		4'b0110 : begin d1 = 7'b0111111; d2 = 7'b1111101; end // 06
		4'b0111 : begin d1 = 7'b0111111; d2 = 7'b0000111; end // 07
		4'b1000 : begin d1 = 7'b0111111; d2 = 7'b1111111; end // 08
		4'b1001 : begin d1 = 7'b0111111; d2 = 7'b1101111; end // 09
		4'b1010 : begin d1 = 7'b0000110; d2 = 7'b0111111; end // 10
		4'b1011 : begin d1 = 7'b0000110; d2 = 7'b0000110; end // 11
		4'b1100 : begin d1 = 7'b0000110; d2 = 7'b1011011; end // 12
		4'b1101 : begin d1 = 7'b0000110; d2 = 7'b1001111; end // 13
		4'b1110 : begin d1 = 7'b0000110; d2 = 7'b1100110; end // 14
		4'b1111 : begin d1 = 7'b0000110; d2 = 7'b1101101; end // 15
		default : begin d1 = 7'b0000000; d2 = 7'b0000000; end
	endcase
	end
	
endmodule;

Lab 3/P3/FA.v
module FA(a,b,cin,cout,s);
	input a,b,cin;
	output cout,s; 
	wire [1:0] sum;
	
	assign sum = a + b + cin;
	assign cout = sum[1];
	assign s = sum[0];

endmodule

Lab 3/P4/fourBit_FA.v
module fourBit_FA(a,b,cin,cout,s);
	// ripple carry adder
	input [3:0] a,b;
	input cin;
	output cout;
	output [3:0] s;
	wire carry1 , carry2, carry3;

	FA fa0(.a(a[0]), .b(b[0]), .cin(cin), .cout(carry1), .s(s[0]));
	FA fa1(.a(a[1]), .b(b[1]), .cin(carry1), .cout(carry2), .s(s[1]));
	FA fa2(.a(a[2]), .b(b[2]), .cin(carry2), .cout(carry3), .s(s[2]));
	FA fa3(.a(a[3]), .b(b[3]), .cin(carry3), .cout(cout), .s(s[3]));

endmodule

Lab 3/P4/BCD_Add.v
module BCD_Add(
    input [3:0] A, B,
    input cin,
    output [6:0] d1, d2, // Outputs for 7-segment display
    output error          // Error signal
);

    wire [3:0] sum;
    wire [3:0] corrected_sum;
    wire carry_out;

    // Step 1: Add A, B, and cin using a 4-bit full adder
    fourBit_FA adder (
        .a(A),
        .b(B),
        .cin(cin),
        .s(sum[3:0]),
        .cout(carry_out)
    );

    // Step 2: Check if correction is needed (sum > 9)

    // Step 4: Use lab3_p2_v2 to display the result
    lab3_p2_v2 display (
        .v({sum}),
        .d1(d1),
        .d2(d2)
    );

    // Step 5: Error check for inputs greater than 7
    assign error = (A > 4'b0111) || (B > 4'b0111);

endmodule

Lab 3/P4/TB.v
`timescale 1ns / 1ps
 
module TB;
 
	// ------------------ Instantiate module ------------------
	// We are instantiating the module mux2, naming it instantiate_mux2.
	// select, input1, input2 are controlled by the testbench, output is 
	// checked  within the testbench
 
	reg [3:0] count;
	reg [3:0] input_binarya, input_binaryb;
	wire [6:0] output_7seg1, output_7seg2;
	wire error;
	
	BCD_Add instantiate_BCD_Add(.A(input_binarya), .B(input_binaryb), .cin(1'b0), .d1(output_7seg1), .d2(output_7seg2), .error(error));

	initial begin 
		count = 4'b0000;
	end
	
	always begin
		#50
		count=count+4'b0001;
	end
	
	always @(count) begin
		case (count)
		4'b0000 : begin input_binarya = 4'b0000; input_binaryb = 4'b0000; end
		4'b0001 : begin input_binarya = 4'b0001; input_binaryb = 4'b0001; end
		4'b0010 : begin input_binarya = 4'b0010; input_binaryb = 4'b0010; end
		4'b0011 : begin input_binarya = 4'b0011; input_binaryb = 4'b0011; end
		4'b0100 : begin input_binarya = 4'b0100; input_binaryb = 4'b0100; end
		4'b0101 : begin input_binarya = 4'b0101; input_binaryb = 4'b0101; end
		4'b0110 : begin input_binarya = 4'b0110; input_binaryb = 4'b0110; end
		default : begin input_binarya = 4'b0011; input_binaryb = 4'b0011; end
	endcase
	end
    initial begin
        // Initialize VCD dump
        $dumpfile("TB.vcd");
        $dumpvars(0, TB);
        
        #500 $finish;
    end
 
endmodule

Lab 3/P4/TB.vcd
$date
	Thu Mar 27 17:05:40 2025
$end
$version
	Icarus Verilog
$end
$timescale
	1ps
$end
$scope module TB $end
$var wire 7 ! output_7seg2 [6:0] $end
$var wire 7 " output_7seg1 [6:0] $end
$var wire 1 # error $end
$var reg 4 $ count [3:0] $end
$var reg 4 % input_binarya [3:0] $end
$var reg 4 & input_binaryb [3:0] $end
$scope module instantiate_BCD_Add $end
$var wire 4 ' A [3:0] $end
$var wire 4 ( B [3:0] $end
$var wire 1 ) cin $end
$var wire 1 # error $end
$var wire 4 * sum [3:0] $end
$var wire 7 + d2 [6:0] $end
$var wire 7 , d1 [6:0] $end
$var wire 1 - carry_out $end
$scope module adder $end
$var wire 4 . a [3:0] $end
$var wire 4 / b [3:0] $end
$var wire 1 ) cin $end
$var wire 4 0 s [3:0] $end
$var wire 1 - cout $end
$var wire 1 1 carry3 $end
$var wire 1 2 carry2 $end
$var wire 1 3 carry1 $end
$scope module fa0 $end
$var wire 1 4 a $end
$var wire 1 5 b $end
$var wire 1 ) cin $end
$var wire 2 6 sum [1:0] $end
$var wire 1 7 s $end
$var wire 1 3 cout $end
$upscope $end
$scope module fa1 $end
$var wire 1 8 a $end
$var wire 1 9 b $end
$var wire 1 3 cin $end
$var wire 2 : sum [1:0] $end
$var wire 1 ; s $end
$var wire 1 2 cout $end
$upscope $end
$scope module fa2 $end
$var wire 1 < a $end
$var wire 1 = b $end
$var wire 1 2 cin $end
$var wire 2 > sum [1:0] $end
$var wire 1 ? s $end
$var wire 1 1 cout $end
$upscope $end
$scope module fa3 $end
$var wire 1 @ a $end
$var wire 1 A b $end
$var wire 1 1 cin $end
$var wire 2 B sum [1:0] $end
$var wire 1 C s $end
$var wire 1 - cout $end
$upscope $end
$upscope $end
$scope module display $end
$var wire 4 D v [3:0] $end
$var reg 7 E d1 [6:0] $end
$var reg 7 F d2 [6:0] $end
$upscope $end
$upscope $end
$upscope $end
$enddefinitions $end
$comment Show the parameter values. $end
$dumpall
$end
#0
$dumpvars
b111111 F
b111111 E
b0 D
0C
b0 B
0A
0@
0?
b0 >
0=
0<
0;
b0 :
09
08
07
b0 6
05
04
03
02
01
b0 0
b0 /
b0 .
0-
b111111 ,
b111111 +
b0 *
0)
b0 (
b0 '
b0 &
b0 %
b0 $
0#
b111111 "
b111111 !
$end
#50000
b1011011 !
b1011011 +
b1011011 F
b10 D
b10 *
b10 0
1;
b1 :
13
15
b10 6
14
b1 &
b1 (
b1 /
b1 %
b1 '
b1 .
b1 $
#100000
b1100110 !
b1100110 +
b1100110 F
0;
b100 D
b100 *
b100 0
1?
03
b1 >
12
05
19
b0 6
04
b10 :
18
b10 &
b10 (
b10 /
b10 %
b10 '
b10 .
b10 $
#150000
b1111101 !
b1111101 +
b1111101 F
b110 D
b110 *
b110 0
1;
b11 :
13
15
b10 6
14
b11 &
b11 (
b11 /
b11 %
b11 '
b11 .
b11 $
#200000
b1111111 !
b1111111 +
b1111111 F
0?
0;
b1000 D
b1000 *
b1000 0
1C
02
03
b1 B
11
05
09
1=
b0 6
04
b0 :
08
b10 >
1<
b100 &
b100 (
b100 /
b100 %
b100 '
b100 .
b100 $
#250000
b111111 !
b111111 +
b111111 F
b110 "
b110 ,
b110 E
b1010 D
b1010 *
b1010 0
1;
b1 :
13
15
b10 6
14
b101 &
b101 (
b101 /
b101 %
b101 '
b101 .
b101 $
#300000
b1011011 !
b1011011 +
b1011011 F
0;
b1100 D
b1100 *
b1100 0
1?
03
b11 >
12
05
19
b0 6
04
b10 :
18
b110 &
b110 (
b110 /
b110 %
b110 '
b110 .
b110 $
#350000
b1111101 !
b1111101 +
b1111101 F
b111111 "
b111111 ,
b111111 E
1;
b110 D
b110 *
b110 0
0C
b11 :
13
b0 B
01
15
0=
b10 6
14
b1 >
0<
b11 &
b11 (
b11 /
b11 %
b11 '
b11 .
b111 $
#400000
b1000 $
#450000
b1001 $
#500000
b1010 $
