Lab 5/P1/toggleflip.v
module toggleflip (enable, clock, clear, Q, Qnot);
    input  enable, clock, clear;
    output Q, Qnot;

    reg Q, Qnot;

    // Initialize Q and Qnot
    initial begin
        Q = 0;
        Qnot = 1;
    end

    always @ (posedge clock or posedge clear or negedge clock) begin
        if (clear) begin
            Q <= 0;
            Qnot <= 1;
        end else if (enable) begin
            Q <= ~Q;
            Qnot <= ~Qnot;
        end
    end
endmodule

Lab 5/P1/counter.v
module counter (clock, clear, enable, Q);
    input  clock, clear, enable;
    output [3:0] Q;

    wire Qnotnot;

    toggleflip T1 (enable, clock, clear, Q[0], Qnotnot);
    toggleflip T2 (enable && Q[0], clock, clear, Q[1], Qnotnot);
    toggleflip T3 (enable && Q[0] && Q[1], clock, clear, Q[2], Qnotnot);
    toggleflip T4 (enable && Q[0] && Q[1] && Q[2], clock, clear, Q[3], Qnotnot);

endmodule

Lab 5/P1/TB.v
`timescale 1ns / 1ps
 
module TB;
 
	// ------------------ Instantiate module ------------------
	// We are instantiating the module counter, and testing with the relevant signals
	
	reg [3:0] count;
    reg Din,Clkin,clear;
    wire [3:0] Q;
	
	// instantiate the counter

    counter instantiate_counter (Clkin, clear, Din, Q);
	
	initial begin 
		count = 4'b0000;
		Clkin =1'b0;
        clear = 1'b1; // Assert clear
        #50 clear = 1'b0; // Deassert clear after 50 time units
	end
	
	always begin
		#50
		count=count+4'b0001;
	end
	
	always begin
		#10
		Clkin = 1'b0;
		#10
		Clkin = 1'b1;
	end	

	
	always @(count) begin
		case (count)
		4'b0000 : begin Din = 1'b1; end
		4'b0001 : begin Din = 1'b1; end
		4'b0010 : begin Din = 1'b1; end
		4'b0011 : begin Din = 1'b1; end
		4'b0100 : begin Din = 1'b1; end
		4'b0101 : begin Din = 1'b1; end
		4'b0110 : begin Din = 1'b1; end
		4'b0111 : begin Din = 1'b1; end
		4'b1000 : begin Din = 1'b1; end
		4'b1001 : begin Din = 1'b0; end
		4'b1010 : begin Din = 1'b0; end
		4'b1011 : begin Din = 1'b0; end
		4'b1100 : begin Din = 1'b0; end
		4'b1101 : begin Din = 1'b0; end
		4'b1110 : begin Din = 1'b0; end
		4'b1111 : begin Din = 1'b0; end
		default : begin Din = 1'b0; end
	endcase
	end

      initial begin
        // Initialize VCD dump
        $dumpfile("TB.vcd");
        $dumpvars(0, TB);
        
        #1000 $finish;
    end
endmodule

Lab 5/P1/TB.vcd
$date
	Thu Apr 10 13:06:30 2025
$end
$version
	Icarus Verilog
$end
$timescale
	1ps
$end
$scope module TB $end
$var wire 4 ! Q [3:0] $end
$var reg 1 " Clkin $end
$var reg 1 # Din $end
$var reg 1 $ clear $end
$var reg 4 % count [3:0] $end
$scope module instantiate_counter $end
$var wire 1 & Qnotnot $end
$var wire 1 $ clear $end
$var wire 1 " clock $end
$var wire 1 # enable $end
$var wire 4 ' Q [3:0] $end
$scope module T1 $end
$var wire 1 $ clear $end
$var wire 1 " clock $end
$var wire 1 # enable $end
$var reg 1 ( Q $end
$var reg 1 ) Qnot $end
$upscope $end
$scope module T2 $end
$var wire 1 $ clear $end
$var wire 1 " clock $end
$var wire 1 * enable $end
$var reg 1 + Q $end
$var reg 1 , Qnot $end
$upscope $end
$scope module T3 $end
$var wire 1 $ clear $end
$var wire 1 " clock $end
$var wire 1 - enable $end
$var reg 1 . Q $end
$var reg 1 / Qnot $end
$upscope $end
$scope module T4 $end
$var wire 1 $ clear $end
$var wire 1 " clock $end
$var wire 1 0 enable $end
$var reg 1 1 Q $end
$var reg 1 2 Qnot $end
$upscope $end
$upscope $end
$upscope $end
$enddefinitions $end
$comment Show the parameter values. $end
$dumpall
$end
#0
$dumpvars
12
01
00
1/
0.
0-
1,
0+
0*
1)
0(
b0 '
1&
b0 %
1$
1#
0"
b0 !
$end
#20000
1"
#30000
0"
#40000
1"
#50000
1*
x&
0)
b1 !
b1 '
1(
0"
b1 %
0$
#60000
0*
0,
1+
x&
1)
b10 !
b10 '
0(
1"
#70000
1-
1*
0)
b11 !
b11 '
1(
0"
#80000
0-
0*
0/
1.
x&
1,
0+
1)
b100 !
b100 '
0(
1"
#90000
1*
0)
b101 !
b101 '
1(
0"
#100000
0*
0,
1+
1)
b110 !
b110 '
0(
1"
b10 %
#110000
10
1-
1*
0)
b111 !
b111 '
1(
0"
#120000
00
0-
0*
02
11
x&
1/
0.
1,
0+
1)
b1000 !
b1000 '
0(
1"
#130000
1*
0)
b1001 !
b1001 '
1(
0"
#140000
0*
0,
1+
1)
b1010 !
b1010 '
0(
1"
#150000
1-
1*
0)
b1011 !
b1011 '
1(
0"
b11 %
#160000
0-
0*
0/
1.
1,
0+
1)
b1100 !
b1100 '
0(
1"
#170000
1*
0)
b1101 !
b1101 '
1(
0"
#180000
0*
0,
1+
1)
b1110 !
b1110 '
0(
1"
#190000
10
1-
1*
0&
0)
b1111 !
b1111 '
1(
0"
#200000
00
0-
0*
12
01
1/
0.
1,
0+
1&
1)
b0 !
b0 '
0(
1"
b100 %
#210000
1*
x&
0)
b1 !
b1 '
1(
0"
#220000
0*
0,
1+
x&
1)
b10 !
b10 '
0(
1"
#230000
1-
1*
0)
b11 !
b11 '
1(
0"
#240000
0-
0*
0/
1.
x&
1,
0+
1)
b100 !
b100 '
0(
1"
#250000
1*
0)
b101 !
b101 '
1(
0"
b101 %
#260000
0*
0,
1+
1)
b110 !
b110 '
0(
1"
#270000
10
1-
1*
0)
b111 !
b111 '
1(
0"
#280000
00
0-
0*
02
11
x&
1/
0.
1,
0+
1)
b1000 !
b1000 '
0(
1"
#290000
1*
0)
b1001 !
b1001 '
1(
0"
#300000
0*
0,
1+
1)
b1010 !
b1010 '
0(
1"
b110 %
#310000
1-
1*
0)
b1011 !
b1011 '
1(
0"
#320000
0-
0*
0/
1.
1,
0+
1)
b1100 !
b1100 '
0(
1"
#330000
1*
0)
b1101 !
b1101 '
1(
0"
#340000
0*
0,
1+
1)
b1110 !
b1110 '
0(
1"
#350000
10
1-
1*
0&
0)
b1111 !
b1111 '
1(
0"
b111 %
#360000
00
0-
0*
12
01
1/
0.
1,
0+
1&
1)
b0 !
b0 '
0(
1"
#370000
1*
x&
0)
b1 !
b1 '
1(
0"
#380000
0*
0,
1+
x&
1)
b10 !
b10 '
0(
1"
#390000
1-
1*
0)
b11 !
b11 '
1(
0"
#400000
0-
0*
0/
1.
x&
1,
0+
1)
b100 !
b100 '
0(
1"
b1000 %
#410000
1*
0)
b101 !
b101 '
1(
0"
#420000
0*
0,
1+
1)
b110 !
b110 '
0(
1"
#430000
10
1-
1*
0)
b111 !
b111 '
1(
0"
#440000
00
0-
0*
02
11
x&
1/
0.
1,
0+
1)
b1000 !
b1000 '
0(
1"
#450000
0#
0"
b1001 %
#460000
1"
#470000
0"
#480000
1"
#490000
0"
#500000
1"
b1010 %
#510000
0"
#520000
1"
#530000
0"
#540000
1"
#550000
0"
b1011 %
#560000
1"
#570000
0"
#580000
1"
#590000
0"
#600000
1"
b1100 %
#610000
0"
#620000
1"
#630000
0"
#640000
1"
#650000
0"
b1101 %
#660000
1"
#670000
0"
#680000
1"
#690000
0"
#700000
1"
b1110 %
#710000
0"
#720000
1"
#730000
0"
#740000
1"
#750000
0"
b1111 %
#760000
1"
#770000
0"
#780000
1"
#790000
0"
#800000
1*
0)
b1001 !
b1001 '
1(
1#
1"
b0 %
#810000
0*
0-
1)
0(
0,
b1010 !
b1010 '
1+
0"
#820000
1-
1*
0)
b1011 !
b1011 '
1(
1"
#830000
0*
0-
00
1)
0(
1,
0+
x&
0/
b1100 !
b1100 '
1.
0"
#840000
1*
0)
b1101 !
b1101 '
1(
1"
#850000
00
0*
0-
1)
0(
x&
0,
b1110 !
b1110 '
1+
0"
b1 %
#860000
10
1-
1*
0&
0)
b1111 !
b1111 '
1(
1"
#870000
0*
0-
00
1)
0(
1,
0+
1/
0.
1&
12
b0 !
b0 '
01
0"
#880000
1*
x&
0)
b1 !
b1 '
1(
1"
#890000
0*
0-
1)
0(
0,
b10 !
b10 '
1+
0"
#900000
1-
1*
0)
b11 !
b11 '
1(
1"
b10 %
#910000
0*
0-
00
1)
0(
1,
0+
0/
b100 !
b100 '
1.
0"
#920000
1*
0)
b101 !
b101 '
1(
1"
#930000
00
0*
0-
1)
0(
0,
b110 !
b110 '
1+
0"
#940000
10
1-
1*
0)
b111 !
b111 '
1(
1"
#950000
0*
0-
00
1)
0(
1,
0+
1/
0.
x&
02
b1000 !
b1000 '
11
0"
b11 %
#960000
1*
0)
b1001 !
b1001 '
1(
1"
#970000
0*
0-
1)
0(
0,
b1010 !
b1010 '
1+
0"
#980000
1-
1*
0)
b1011 !
b1011 '
1(
1"
#990000
0*
0-
00
1)
0(
1,
0+
x&
0/
b1100 !
b1100 '
1.
0"
#1000000
1*
0)
b1101 !
b1101 '
1(
1"
b100 %
