Lab 3/P2/four_bit_2to1muxV2.v
module four_bit_2to1mux (sel,a,b,chosen);
 
	input sel;
	input[3:0] a, b;
	output reg[3:0] chosen;
	
	always @(a,b,sel) begin
		if (sel == 1'b1)
			chosen = b;
		else
			chosen = a;
	end
 
endmodule

Lab 2/P1/part1_TB.v
`timescale 1ns / 1ps
 
module part1_TB;
 
	// ------------------ Instantiate module ------------------
	// We are instantiating the module mux2, naming it instantiate_mux2.
	// select, input1, input2 are controlled by the testbench, output is 
	// checked  within the testbench
 
	reg [3:0] count;
	reg select;
	reg [3:0] input1, input2;
	wire [3:0] output1;
	
	four_bit_2to1mux instantiate_mux4(.sel(select),.a(input1),.b(input2),.chosen(output1));
 	
	initial begin 
		count = 4'b0000;
	end
	
	always begin
		#50
		count=count+4'b0001;
	end
	
	always @(count) begin
		case (count)
		4'b0000 : begin input1 = 4'b0000; input2 = 4'b0001; select = 1'b0; end
		4'b0001 : begin input1 = 4'b0010; input2 = 4'b0011; select = 1'b1; end
		4'b0010 : begin input1 = 4'b0100; input2 = 4'b0111; select = 1'b0; end 
		4'b0011 : begin input1 = 4'b1000; input2 = 4'b1111; select = 1'b1; end
		default : begin input1 = 4'b0000; input2 = 4'b0000; select = 1'b0; end
	endcase
	end

     // Terminate the simulation after a certain period
    initial begin
        // Initialize VCD dump
        $dumpfile("testbench.vcd");
        $dumpvars(0, part1_TB);
        
        #500 $finish;
    end
 
endmodule

Lab 2/P1/4b_testbenchV2.vcd
$date
	Thu Mar 20 12:47:18 2025
$end
$version
	Icarus Verilog
$end
$timescale
	1ps
$end
$scope module part1_TB $end
$var wire 4 ! output1 [3:0] $end
$var reg 4 " count [3:0] $end
$var reg 4 # input1 [3:0] $end
$var reg 4 $ input2 [3:0] $end
$var reg 1 % select $end
$scope module instantiate_mux4 $end
$var wire 4 & a [3:0] $end
$var wire 4 ' b [3:0] $end
$var wire 1 % sel $end
$var reg 4 ( chosen [3:0] $end
$upscope $end
$upscope $end
$enddefinitions $end
$comment Show the parameter values. $end
$dumpall
$end
#0
$dumpvars
b0 (
b1 '
b0 &
0%
b1 $
b0 #
b0 "
b0 !
$end
#50000
b11 !
b11 (
1%
b11 $
b11 '
b10 #
b10 &
b1 "
#100000
b100 !
b100 (
0%
b111 $
b111 '
b100 #
b100 &
b10 "
#150000
b1111 !
b1111 (
1%
b1111 $
b1111 '
b1000 #
b1000 &
b11 "
#200000
b0 !
b0 (
0%
b0 $
b0 '
b0 #
b0 &
b100 "
#250000
b101 "
#300000
b110 "
#350000
b111 "
#400000
b1000 "
#450000
b1001 "
#500000
b1010 "
