Lab 3/P2/lab3_p2_v2.v
module lab3_p2_v2 (v, d1, d2);
    input [3:0] v; 
	output reg[6:0] d1, d2; 
	
	always @(v) begin
		case (v)
		4'b0000 : begin d1 = 7'b0111111; d2 = 7'b0111111; end // 00
		4'b0001 : begin d1 = 7'b0111111; d2 = 7'b0000110; end // 01
		4'b0010 : begin d1 = 7'b0111111; d2 = 7'b1011011; end // 02
		4'b0011 : begin d1 = 7'b0111111; d2 = 7'b1001111; end // 03
		4'b0100 : begin d1 = 7'b0111111; d2 = 7'b1100110; end // 04
		4'b0101 : begin d1 = 7'b0111111; d2 = 7'b1101101; end // 05
		4'b0110 : begin d1 = 7'b0111111; d2 = 7'b1111101; end // 06
		4'b0111 : begin d1 = 7'b0111111; d2 = 7'b0000111; end // 07
		4'b1000 : begin d1 = 7'b0111111; d2 = 7'b1111111; end // 08
		4'b1001 : begin d1 = 7'b0111111; d2 = 7'b1101111; end // 09
		4'b1010 : begin d1 = 7'b0000110; d2 = 7'b0111111; end // 10
		4'b1011 : begin d1 = 7'b0000110; d2 = 7'b0000110; end // 11
		4'b1100 : begin d1 = 7'b0000110; d2 = 7'b1011011; end // 12
		4'b1101 : begin d1 = 7'b0000110; d2 = 7'b1001111; end // 13
		4'b1110 : begin d1 = 7'b0000110; d2 = 7'b1100110; end // 14
		4'b1111 : begin d1 = 7'b0000110; d2 = 7'b1101101; end // 15
		default : begin d1 = 7'b0000000; d2 = 7'b0000000; end
	endcase
	end
	
endmodule;

Lab 3/P2/lab3_p2_TBv2.v
`timescale 1ns / 1ps
 
module lab3_p2_TBv2;
 
	// ------------------ Instantiate module ------------------
	// We are instantiating the module mux2, naming it instantiate_mux2.
	// select, input1, input2 are controlled by the testbench, output is 
	// checked  within the testbench
 
	reg [3:0] count;
	reg [3:0] input_binary;
	wire [6:0] output_7seg1, output_7seg2;
	
	lab3_p2_v2 instantiate_lab3_p2_v2(.v(input_binary), .d1(output_7seg1), .d2(output_7seg2));
 	
	initial begin 
		count = 4'b0000;
	end
	
	always begin
		#50
		count=count+4'b0001;
	end
	
	always @(count) begin
		case (count)
		4'b0000 : begin input_binary = 4'b0000; end
		4'b0001 : begin input_binary = 4'b0101; end
		4'b0010 : begin input_binary = 4'b1010; end
		4'b0011 : begin input_binary = 4'b1011; end
		4'b0100 : begin input_binary = 4'b1100; end
		4'b0101 : begin input_binary = 4'b1101; end
		4'b0110 : begin input_binary = 4'b1110; end
		default : begin input_binary = 4'b0011; end
	endcase
	end
    initial begin
        // Initialize VCD dump
        $dumpfile("testbenchv2.vcd");
        $dumpvars(0, lab3_p2_TBv2);
        
        #500 $finish;
    end
 
endmodule

Lab 3/P2/testbenchv2.vcd
$date
	Thu Mar 27 15:58:38 2025
$end
$version
	Icarus Verilog
$end
$timescale
	1ps
$end
$scope module lab3_p2_TBv2 $end
$var wire 7 ! output_7seg2 [6:0] $end
$var wire 7 " output_7seg1 [6:0] $end
$var reg 4 # count [3:0] $end
$var reg 4 $ input_binary [3:0] $end
$scope module instantiate_lab3_p2_v2 $end
$var wire 4 % v [3:0] $end
$var reg 7 & d1 [6:0] $end
$var reg 7 ' d2 [6:0] $end
$upscope $end
$upscope $end
$enddefinitions $end
$comment Show the parameter values. $end
$dumpall
$end
#0
$dumpvars
b111111 '
b111111 &
b0 %
b0 $
b0 #
b111111 "
b111111 !
$end
#50000
b1101101 !
b1101101 '
b101 $
b101 %
b1 #
#100000
b111111 !
b111111 '
b110 "
b110 &
b1010 $
b1010 %
b10 #
#150000
b110 !
b110 '
b1011 $
b1011 %
b11 #
#200000
b1011011 !
b1011011 '
b1100 $
b1100 %
b100 #
#250000
b1001111 !
b1001111 '
b1101 $
b1101 %
b101 #
#300000
b1100110 !
b1100110 '
b1110 $
b1110 %
b110 #
#350000
b1001111 !
b1001111 '
b111111 "
b111111 &
b11 $
b11 %
b111 #
#400000
b1000 #
#450000
b1001 #
#500000
b1010 #
