Lab 3/P2/binary_to_7Seg.v
module binary_to_7Seg(binary, sevenSeg);

    input [3:0] binary;
    output reg [6:0] sevenSeg;

    always @(binary) begin
        case (binary)
            4'b0000: sevenSeg = 7'b0111111; // 0
            4'b0001: sevenSeg = 7'b0000110; // 1
            4'b0010: sevenSeg = 7'b1011011; // 2
            4'b0011: sevenSeg = 7'b1001111; // 3
            4'b0100: sevenSeg = 7'b1100110; // 4
            4'b0101: sevenSeg = 7'b1101101; // 5
            4'b0110: sevenSeg = 7'b1111101; // 6
            4'b0111: sevenSeg = 7'b0000111; // 7
            4'b1000: sevenSeg = 7'b1111111; // 8
            4'b1001: sevenSeg = 7'b1101111; // 9
            default: sevenSeg = 7'b0000000; // Don't care (all segments off)
        endcase
    end

endmodule

module dual_binary_to_7Seg(binary1, binary0, sevenSeg1, sevenSeg0);

    input [3:0] binary1, binary0;
    output [6:0] sevenSeg1, sevenSeg0;

    // Instantiate two binary_to_7Seg modules
    binary_to_7Seg display1 (
        .binary(binary1),
        .sevenSeg(sevenSeg1)
    );

    binary_to_7Seg display0 (
        .binary(binary0),
        .sevenSeg(sevenSeg0)
    );

endmodule

Lab 3/P2/four_bit_2to1muxV2.v
module four_bit_2to1mux (sel,a,b,chosen);
 
	input sel;
	input[3:0] a, b;
	output reg[3:0] chosen;
	
	always @(a,b,sel) begin
		if (sel == 1'b1)
			chosen = b;
		else
			chosen = a;
	end
 
endmodule

Lab 3/P2/circuitB.v
module circuitB (z, d1);
    input z;
	output reg[6:0] d1; 
	
	always @(z)
	begin
	  if (z == 1'b0)
		d1 = 7'b0111111;
	  else
		d1 = 7'b0000110;
	end
endmodule;

Lab 3/P2/comparator.v
module comparator (v, z);
	input [3:0] v; 	
	output reg z; 
	// if v is >9, z = 1, else z = 0
	always @(v)
	begin
	  if (v > 4'b1001) // Check if v is greater than 9
		z = 1;         // Set z to 1 if condition is true
	  else
		z = 0;         // Set z to 0 otherwise
	end
endmodule;

Lab 3/P2/circuitA.v
module circuitA (v, A);
    input [3:0] v;
    output reg [3:0] A; // Changed to reg since it's assigned in an always block
  
    always @(v) begin
        case (v)
            4'b1010: A = 4'b0000; // 10 -> 0
            4'b1011: A = 4'b0001; // 11 -> 1
            4'b1100: A = 4'b0010; // 12 -> 2
            4'b1101: A = 4'b0011; // 13 -> 3
            4'b1110: A = 4'b0100; // 14 -> 4
            4'b1111: A = 4'b0101; // 15 -> 5
            default: A = 4'b0000; // Default case
        endcase
    end
endmodule;

Lab 3/P2/lab3_p2_v1.v
module lab3_p2_v1 (v, d1, d2);
    input [3:0] v; 
	output [6:0] d1, d2; 
	
	//Add any required intermediate wires here
	wire [3:0] a, b;
	wire z;
	
	circuitA inst_circA(.v(v),.A(a));
	comparator inst_comp(.v(v),.z(z));
	circuitB inst_circB(.z(z),.d1(d1));
	four_bit_2to1mux inst_mux(.sel(z),.a(v),.b(a),.chosen(b));
	binary_to_7Seg instantiate_bto7seg(.binary(b),.sevenSeg(d2));
	
endmodule;

Lab 3/P2/lab3_p2_TB.v
`timescale 1ns / 1ps
 
module lab3_p2_TB;
 
	// ------------------ Instantiate module ------------------
	// We are instantiating the module mux2, naming it instantiate_mux2.
	// select, input1, input2 are controlled by the testbench, output is 
	// checked  within the testbench
 
	reg [3:0] count;
	reg [3:0] input_binary;
	wire [6:0] output_7seg1, output_7seg2;
	
	lab3_p2_v1 instantiate_lab3_p2_v1(.v(input_binary), .d1(output_7seg1), .d2(output_7seg2));
 	
	initial begin 
		count = 4'b0000;
	end
	
	always begin
		#50
		count=count+4'b0001;
	end
	
	always @(count) begin
		case (count)
		4'b0000 : begin input_binary = 4'b0000; end
		4'b0001 : begin input_binary = 4'b0101; end
		4'b0010 : begin input_binary = 4'b1010; end
		4'b0011 : begin input_binary = 4'b1011; end
		4'b0100 : begin input_binary = 4'b1100; end
		4'b0101 : begin input_binary = 4'b1101; end
		4'b0110 : begin input_binary = 4'b1110; end
		default : begin input_binary = 4'b0011; end
	endcase
	end

    initial begin
        // Initialize VCD dump
        $dumpfile("testbench.vcd");
        $dumpvars(0, lab3_p2_TB);
        
        #500 $finish;
    end
 
endmodule

Lab 3/P2/testbench.vcd
$date
	Thu Mar 27 16:04:43 2025
$end
$version
	Icarus Verilog
$end
$timescale
	1ps
$end
$scope module lab3_p2_TB $end
$var wire 7 ! output_7seg2 [6:0] $end
$var wire 7 " output_7seg1 [6:0] $end
$var reg 4 # count [3:0] $end
$var reg 4 $ input_binary [3:0] $end
$scope module instantiate_lab3_p2_v1 $end
$var wire 4 % v [3:0] $end
$var wire 1 & z $end
$var wire 7 ' d2 [6:0] $end
$var wire 7 ( d1 [6:0] $end
$var wire 4 ) b [3:0] $end
$var wire 4 * a [3:0] $end
$scope module inst_circA $end
$var wire 4 + v [3:0] $end
$var reg 4 , A [3:0] $end
$upscope $end
$scope module inst_circB $end
$var wire 1 & z $end
$var reg 7 - d1 [6:0] $end
$upscope $end
$scope module inst_comp $end
$var wire 4 . v [3:0] $end
$var reg 1 & z $end
$upscope $end
$scope module inst_mux $end
$var wire 4 / a [3:0] $end
$var wire 4 0 b [3:0] $end
$var wire 1 & sel $end
$var reg 4 1 chosen [3:0] $end
$upscope $end
$scope module instantiate_bto7seg $end
$var wire 4 2 binary [3:0] $end
$var reg 7 3 sevenSeg [6:0] $end
$upscope $end
$upscope $end
$upscope $end
$enddefinitions $end
$comment Show the parameter values. $end
$dumpall
$end
#0
$dumpvars
b111111 3
b0 2
b0 1
b0 0
b0 /
b0 .
b111111 -
b0 ,
b0 +
b0 *
b0 )
b111111 (
b111111 '
0&
b0 %
b0 $
b0 #
b111111 "
b111111 !
$end
#50000
b1101101 !
b1101101 '
b1101101 3
b101 )
b101 1
b101 2
b101 $
b101 %
b101 +
b101 .
b101 /
b1 #
#100000
b110 "
b110 (
b110 -
b111111 !
b111111 '
b111111 3
1&
b0 )
b0 1
b0 2
b1010 $
b1010 %
b1010 +
b1010 .
b1010 /
b10 #
#150000
b110 !
b110 '
b110 3
b1 )
b1 1
b1 2
b1 *
b1 ,
b1 0
b1011 $
b1011 %
b1011 +
b1011 .
b1011 /
b11 #
#200000
b1011011 !
b1011011 '
b1011011 3
b10 )
b10 1
b10 2
b10 *
b10 ,
b10 0
b1100 $
b1100 %
b1100 +
b1100 .
b1100 /
b100 #
#250000
b1001111 !
b1001111 '
b1001111 3
b11 )
b11 1
b11 2
b11 *
b11 ,
b11 0
b1101 $
b1101 %
b1101 +
b1101 .
b1101 /
b101 #
#300000
b1100110 !
b1100110 '
b1100110 3
b100 )
b100 1
b100 2
b100 *
b100 ,
b100 0
b1110 $
b1110 %
b1110 +
b1110 .
b1110 /
b110 #
#350000
b1001111 !
b1001111 '
b1001111 3
b111111 "
b111111 (
b111111 -
b11 )
b11 1
b11 2
b0 *
b0 ,
b0 0
0&
b11 $
b11 %
b11 +
b11 .
b11 /
b111 #
#400000
b1000 #
#450000
b1001 #
#500000
b1010 #
