Lab 4/P3/lab4_part3_TB.v
`timescale 1ns / 1ps
 
module lab4_part3_TB;
 
	// ------------------ Instantiate module ------------------
	
	reg [3:0] count;
	reg Din,Clkin;
	wire Qout,Qnotout;
	
	// instantiate and connect master_slave here
	
	initial begin 
		count = 4'b0000;
		Clkin =1'b0;
	end
	
	always begin
		#50
		count=count+4'b0001;
	end
	
	always begin
		#100
		Clkin = 1'b0;
		#100
		Clkin = 1'b1;
	end	

	
	always @(count) begin
		case (count)
		4'b0000 : begin Din = 1'b0; end
		4'b0001 : begin Din = 1'b0; end
		4'b0010 : begin Din = 1'b0; end
		4'b0011 : begin Din = 1'b0; end
		4'b0100 : begin Din = 1'b1; end
		4'b0101 : begin Din = 1'b1; end
		4'b0110 : begin Din = 1'b1; end
		4'b0111 : begin Din = 1'b1; end
		4'b1000 : begin Din = 1'b1; end
		4'b1001 : begin Din = 1'b0; end
		4'b1010 : begin Din = 1'b0; end
		4'b1011 : begin Din = 1'b0; end
		4'b1100 : begin Din = 1'b1; end
		4'b1101 : begin Din = 1'b0; end
		4'b1110 : begin Din = 1'b0; end
		4'b1111 : begin Din = 1'b0; end
		default : begin Din = 1'b0; end
	endcase
	end

	     initial begin
        // Initialize VCD dump
        $dumpfile("TB.vcd");
        $dumpvars(0, lab4_part3_TB);
        
        #1000 $finish;
    end

 
endmodule

Lab 4/P3/TB.vcd
$date
	Thu Apr  3 13:17:31 2025
$end
$version
	Icarus Verilog
$end
$timescale
	1ps
$end
$scope module lab4_part3_TB $end
$var reg 1 ! Clkin $end
$var reg 1 " Din $end
$var reg 4 # count [3:0] $end
$upscope $end
$enddefinitions $end
$comment Show the parameter values. $end
$dumpall
$end
#0
$dumpvars
b0 #
0"
0!
$end
#50000
b1 #
#100000
b10 #
#150000
b11 #
#200000
1"
b100 #
1!
#250000
b101 #
#300000
b110 #
0!
#350000
b111 #
#400000
b1000 #
1!
#450000
0"
b1001 #
#500000
b1010 #
0!
#550000
b1011 #
#600000
1"
b1100 #
1!
#650000
0"
b1101 #
#700000
b1110 #
0!
#750000
b1111 #
#800000
b0 #
1!
#850000
b1 #
#900000
b10 #
0!
#950000
b11 #
#1000000
1"
b100 #
1!
