Lab 3/P3/FA.v
module FA(a,b,cin,cout,s);
	input a,b,cin;
	output cout,s; 
	wire [1:0] sum;
	
	assign sum = a + b + cin;
	assign cout = sum[1];
	assign s = sum[0];

endmodule

Lab 3/P4/fourBit_FA.v
module fourBit_FA(a,b,cin,cout,s);
	// ripple carry adder
	input [3:0] a,b;
	input cin;
	output cout;
	output [3:0] s;
	wire carry1 , carry2, carry3;

	FA fa0(.a(a[0]), .b(b[0]), .cin(cin), .cout(carry1), .s(s[0]));
	FA fa1(.a(a[1]), .b(b[1]), .cin(carry1), .cout(carry2), .s(s[1]));
	FA fa2(.a(a[2]), .b(b[2]), .cin(carry2), .cout(carry3), .s(s[2]));
	FA fa3(.a(a[3]), .b(b[3]), .cin(carry3), .cout(cout), .s(s[3]));

endmodule

Lab 3/P3/lab3_p3_TB.v
`timescale 1ns / 1ps
module lab3_p3_TB;

    reg [3:0] count;
    reg [3:0] a, b;
    reg cin;
    wire cout;
    wire [3:0] s;

    // Instantiate and connect fourBit_FA
    fourBit_FA fourBit_FA0 (
        .a(a),
        .b(b),
        .cin(cin),
        .cout(cout),
        .s(s)
    );

    initial begin 
        count = 4'b0000;
    end

    always begin
        #50
        count = count + 4'b0001;
    end

    always @(count) begin
        case (count)
            4'b0000 : begin a = 4'b0000; b = 4'b0000; cin = 1'b0; end
            4'b0001 : begin a = 4'b0000; b = 4'b0001; cin = 1'b0; end
            4'b0010 : begin a = 4'b0001; b = 4'b0001; cin = 1'b0; end
            4'b0011 : begin a = 4'b0010; b = 4'b0010; cin = 1'b0; end
            4'b0100 : begin a = 4'b0011; b = 4'b0011; cin = 1'b0; end
            4'b0101 : begin a = 4'b0100; b = 4'b0100; cin = 1'b0; end
            4'b0110 : begin a = 4'b0101; b = 4'b0101; cin = 1'b0; end
            4'b0111 : begin a = 4'b0110; b = 4'b0110; cin = 1'b0; end
            default : begin a = 4'b0000; b = 4'b0000; cin = 1'b0; end
        endcase
    end

    initial begin
        // Initialize VCD dump
        $dumpfile("testbench.vcd");
        $dumpvars(0, lab3_p3_TB);
        
        #500 $finish;
    end

endmodule

Lab 3/P3/testbench.vcd
$date
	Thu Mar 27 16:27:47 2025
$end
$version
	Icarus Verilog
$end
$timescale
	1ps
$end
$scope module lab3_p3_TB $end
$var wire 4 ! s [3:0] $end
$var wire 1 " cout $end
$var reg 4 # a [3:0] $end
$var reg 4 $ b [3:0] $end
$var reg 1 % cin $end
$var reg 4 & count [3:0] $end
$scope module fourBit_FA0 $end
$var wire 4 ' a [3:0] $end
$var wire 4 ( b [3:0] $end
$var wire 1 % cin $end
$var wire 4 ) s [3:0] $end
$var wire 1 " cout $end
$var wire 1 * carry3 $end
$var wire 1 + carry2 $end
$var wire 1 , carry1 $end
$scope module fa0 $end
$var wire 1 - a $end
$var wire 1 . b $end
$var wire 1 % cin $end
$var wire 2 / sum [1:0] $end
$var wire 1 0 s $end
$var wire 1 , cout $end
$upscope $end
$scope module fa1 $end
$var wire 1 1 a $end
$var wire 1 2 b $end
$var wire 1 , cin $end
$var wire 2 3 sum [1:0] $end
$var wire 1 4 s $end
$var wire 1 + cout $end
$upscope $end
$scope module fa2 $end
$var wire 1 5 a $end
$var wire 1 6 b $end
$var wire 1 + cin $end
$var wire 2 7 sum [1:0] $end
$var wire 1 8 s $end
$var wire 1 * cout $end
$upscope $end
$scope module fa3 $end
$var wire 1 9 a $end
$var wire 1 : b $end
$var wire 1 * cin $end
$var wire 2 ; sum [1:0] $end
$var wire 1 < s $end
$var wire 1 " cout $end
$upscope $end
$upscope $end
$upscope $end
$enddefinitions $end
$comment Show the parameter values. $end
$dumpall
$end
#0
$dumpvars
0<
b0 ;
0:
09
08
b0 7
06
05
04
b0 3
02
01
00
b0 /
0.
0-
0,
0+
0*
b0 )
b0 (
b0 '
b0 &
0%
b0 $
b0 #
0"
b0 !
$end
#50000
b1 !
b1 )
10
b1 /
1.
b1 $
b1 (
b1 &
#100000
14
b1 3
1,
b10 !
b10 )
00
b10 /
1-
b1 #
b1 '
b10 &
#150000
04
b100 !
b100 )
18
0,
b1 7
1+
0.
12
b0 /
0-
b10 3
11
b10 $
b10 (
b10 #
b10 '
b11 &
#200000
b110 !
b110 )
14
b11 3
1,
1.
b10 /
1-
b11 $
b11 (
b11 #
b11 '
b100 &
#250000
08
04
b1000 !
b1000 )
1<
0+
0,
b1 ;
1*
0.
02
16
b0 /
0-
b0 3
01
b10 7
15
b100 $
b100 (
b100 #
b100 '
b101 &
#300000
b1010 !
b1010 )
14
b1 3
1,
1.
b10 /
1-
b101 $
b101 (
b101 #
b101 '
b110 &
#350000
04
b1100 !
b1100 )
18
0,
b11 7
1+
0.
12
b0 /
0-
b10 3
11
b110 $
b110 (
b110 #
b110 '
b111 &
#400000
0<
b0 !
b0 )
08
b0 ;
0*
0+
02
06
b0 3
01
b0 7
05
b0 $
b0 (
b0 #
b0 '
b1000 &
#450000
b1001 &
#500000
b1010 &
