Lab 2/P2/one_bit_4to1muxV2.v
module one_bit_4to1muxV2 (s,u,v,w,x,m);
 
	input[1:0] s;
	input u,v,w,x;
	output reg m;
	
	reg t1, t2;
	
	always @(u,v,s[0]) begin
		if (s[0] == 1'b0) begin
			t1 = u;
			t2 = w;
		end else begin
			t1 = v;
			t2 = x;
		end
	end
 
	always @(t1,t2,s[1]) begin
		if (s[1] == 1'b0)
			m = t1;
		else
			m = t2;
	end


endmodule

Lab 2/P2/part2_TBV2.v
`timescale 1ns / 1ps
 
module part2_TB;
 
	// ------------------ Instantiate module ------------------
	// We are instantiating the module mux2, naming it instantiate_mux2.
	// select, input1, input2 are controlled by the testbench, output is 
	// checked  within the testbench
 
	reg [3:0] count;
	reg [1:0] select;
	reg  input1, input2, input3, input4;
	wire output1;
	
	one_bit_4to1muxV2 instantiate_mux4(.s(select),.u(input1),.v(input2),.w(input3),.x(input4),.m(output1));
 	
	initial begin 
		count = 4'b0000;
	end
	
	always begin
		#50
		count=count+4'b0001;
	end
	
	always @(count) begin
		case (count)
		4'b0000 : begin input1 = 1'b1; input2 = 1'b0; input3 = 1'b0; input4 = 1'b0; select = 2'b00; end
		4'b0001 : begin input1 = 1'b1; input2 = 1'b0; input3 = 1'b0; input4 = 1'b0; select = 2'b01; end
		4'b0010 : begin input1 = 1'b1; input2 = 1'b0; input3 = 1'b0; input4 = 1'b0; select = 2'b10; end
		4'b0011 : begin input1 = 1'b1; input2 = 1'b0; input3 = 1'b0; input4 = 1'b0; select = 2'b11; end
		4'b0100 : begin input1 = 1'b0; input2 = 1'b1; input3 = 1'b0; input4 = 1'b0; select = 2'b00; end
		4'b0101 : begin input1 = 1'b0; input2 = 1'b1; input3 = 1'b0; input4 = 1'b0; select = 2'b01; end
		4'b0110 : begin input1 = 1'b0; input2 = 1'b1; input3 = 1'b0; input4 = 1'b0; select = 2'b10; end
		4'b0111 : begin input1 = 1'b0; input2 = 1'b1; input3 = 1'b0; input4 = 1'b0; select = 2'b11; end
		4'b1000 : begin input1 = 1'b0; input2 = 1'b0; input3 = 1'b1; input4 = 1'b0; select = 2'b00; end
		4'b1001 : begin input1 = 1'b0; input2 = 1'b0; input3 = 1'b1; input4 = 1'b0; select = 2'b01; end
		4'b1010 : begin input1 = 1'b0; input2 = 1'b0; input3 = 1'b1; input4 = 1'b0; select = 2'b10; end
		4'b1011 : begin input1 = 1'b0; input2 = 1'b0; input3 = 1'b1; input4 = 1'b0; select = 2'b11; end
		4'b1100 : begin input1 = 1'b0; input2 = 1'b0; input3 = 1'b0; input4 = 1'b1; select = 2'b00; end
		4'b1101 : begin input1 = 1'b0; input2 = 1'b0; input3 = 1'b0; input4 = 1'b1; select = 2'b01; end
		4'b1110 : begin input1 = 1'b0; input2 = 1'b0; input3 = 1'b0; input4 = 1'b1; select = 2'b10; end
		4'b1111 : begin input1 = 1'b0; input2 = 1'b0; input3 = 1'b0; input4 = 1'b1; select = 2'b11; end
	endcase
	end

 
      // Terminate the simulation after a certain period
    initial begin
        // Initialize VCD dump
        $dumpfile("testbenchV2.vcd");
        $dumpvars(0, part2_TB);
        
        #500 $finish;
    end

endmodule

Lab 2/P2/testbenchV2.vcd
$date
	Thu Mar 20 13:13:56 2025
$end
$version
	Icarus Verilog
$end
$timescale
	1ps
$end
$scope module part2_TB $end
$var wire 1 ! output1 $end
$var reg 4 " count [3:0] $end
$var reg 1 # input1 $end
$var reg 1 $ input2 $end
$var reg 1 % input3 $end
$var reg 1 & input4 $end
$var reg 2 ' select [1:0] $end
$scope module instantiate_mux4 $end
$var wire 2 ( s [1:0] $end
$var wire 1 # u $end
$var wire 1 $ v $end
$var wire 1 % w $end
$var wire 1 & x $end
$var reg 1 ! m $end
$var reg 1 ) t1 $end
$var reg 1 * t2 $end
$upscope $end
$upscope $end
$enddefinitions $end
$comment Show the parameter values. $end
$dumpall
$end
#0
$dumpvars
0*
1)
b0 (
b0 '
0&
0%
0$
1#
b0 "
1!
$end
#50000
0!
0)
b1 '
b1 (
b1 "
#100000
1)
b10 '
b10 (
b10 "
#150000
0)
b11 '
b11 (
b11 "
#200000
b0 '
b0 (
1$
0#
b100 "
#250000
1!
1)
b1 '
b1 (
b101 "
#300000
0)
0!
b10 '
b10 (
b110 "
#350000
1)
b11 '
b11 (
b111 "
#400000
1*
0)
b0 '
b0 (
1%
0$
b1000 "
#450000
0*
b1 '
b1 (
b1001 "
#500000
1!
1*
b10 '
b10 (
b1010 "
