Lab 3/P1/binary_to_7Seg.v
module binary_to_7Seg(binary, sevenSeg);

	input[3:0] binary;
	output reg[6:0]  sevenSeg;
	
	always @(binary) begin
		case (binary)
		4'b0000 : begin sevenSeg = 7'b???????; end
		...
		default : begin ... end
	endcase
	end
 
endmodule

Lab 3/P1/lab3_p1_TB.v
`timescale 1ns / 1ps
 
module lab3_p1_TB;
 
	// ------------------ Instantiate module ------------------
	// We are instantiating the module mux2, naming it instantiate_mux2.
	// select, input1, input2 are controlled by the testbench, output is 
	// checked  within the testbench
 
	reg [3:0] count;
	reg [3:0] input_binary;
	wire [6:0] output_7seg;
	binary_to_7Seg instantiate_bto7seg(.binary(input_binary),.sevenSeg(output_7seg));
 	
	initial begin 
		count = 4'b0000;
	end
	
	always begin
		#50
		count=count+4'b0001;
	end
	
	always @(count) begin
		case (count)
		4'b0000 : begin input_binary = 4'b0000; end
		4'b0001 : begin input_binary = 4'b0101; end
		4'b0010 : begin input_binary = 4'b1010; end
		default : begin input_binary = 4'b0011; end
	endcase
	end

 
endmodule

Lab 3/P1/testbench.vcd
$date
	Thu Mar 27 15:08:26 2025
$end
$version
	Icarus Verilog
$end
$timescale
	1ps
$end
$scope module lab3_p1_TB $end
$var wire 7 ! output_7seg [6:0] $end
$var reg 4 " count [3:0] $end
$var reg 4 # input_binary [3:0] $end
$scope module instantiate_bto7seg $end
$var wire 4 $ binary [3:0] $end
$var reg 7 % sevenSeg [6:0] $end
$upscope $end
$upscope $end
$enddefinitions $end
$comment Show the parameter values. $end
$dumpall
$end
#0
$dumpvars
b1000000 %
b0 $
b0 #
b0 "
b1000000 !
$end
#50000
b10010 !
b10010 %
b101 #
b101 $
b1 "
#100000
b1111111 !
b1111111 %
b1010 #
b1010 $
b10 "
#150000
b110000 !
b110000 %
b11 #
b11 $
b11 "
#200000
b100 "
#250000
b101 "
#300000
b110 "
#350000
b111 "
#400000
b1000 "
#450000
b1001 "
#500000
b1010 "
