Lab 4/P2/gated_RS.v
module gated_RS (clk, R, S, Q, Qnot);
   input  R, S, clk;
   output Q, Qnot;
	
   wire   R_g, S_g, Qa, Qb /* synthesis keep */;
	
   assign R_g = ~(clk && R);
	assign S_g = ~(clk && S);
	assign Qa = ~(Qb && S_g);
	assign Qb = ~(Qa && R_g);
	
	assign Q = Qa;
	assign Qnot = Qb;
	
endmodule

Lab 4/P1/lab4_part1_TB.v
`timescale 1ns / 1ps
 
module lab4_part1_TB;
 
	// ------------------ Instantiate module ------------------
	// We are instantiating the module gated_RS, naming it instantiate_gated_RS.
	
	reg [3:0] count;
	reg Rin,Sin,Clkin;
	wire Qout,Qnotout;
	
	gated_RS instantiate_gated_RS (
	.clk(Clkin), 
	.R(Rin), 
	.S(Sin), 
	.Q(Qout), 
	.Qnot(Qnotout));
	
	
	initial begin 
		count = 4'b0000;
		Clkin =1'b0;
	end
	
	always begin
		#50
		count=count+4'b0001;
	end
	
	always begin
		#100
		Clkin = 1'b0;
		#100
		Clkin = 1'b1;
	end	

	
	always @(count) begin
		case (count)
		4'b0000 : begin Sin = 1'b0; Rin = 1'b0; end
		4'b0001 : begin Sin = 1'b0; Rin = 1'b0; end
		4'b0010 : begin Sin = 1'b0; Rin = 1'b0; end
		4'b0011 : begin Sin = 1'b0; Rin = 1'b0; end
		4'b0100 : begin Sin = 1'b0; Rin = 1'b0; end
		4'b0101 : begin Sin = 1'b0; Rin = 1'b1; end
		4'b0110 : begin Sin = 1'b0; Rin = 1'b0; end
		4'b0111 : begin Sin = 1'b0; Rin = 1'b0; end
		4'b1000 : begin Sin = 1'b0; Rin = 1'b0; end
		4'b1001 : begin Sin = 1'b1; Rin = 1'b0; end
		4'b1010 : begin Sin = 1'b0; Rin = 1'b0; end
		4'b1011 : begin Sin = 1'b0; Rin = 1'b0; end
		4'b1100 : begin Sin = 1'b1; Rin = 1'b1; end
		4'b1101 : begin Sin = 1'b0; Rin = 1'b0; end
		4'b1110 : begin Sin = 1'b0; Rin = 1'b0; end
		4'b1111 : begin Sin = 1'b0; Rin = 1'b0; end
		default : begin Sin = 1'b0; Rin = 1'b0; end
	endcase
	end
    initial begin
        // Initialize VCD dump
        $dumpfile("TB.vcd");
        $dumpvars(0, lab4_part1_TB);
        
        #500 $finish;
    end
 
endmodule

Lab 4/P1/TB.vcd
$date
	Thu Apr  3 13:00:21 2025
$end
$version
	Icarus Verilog
$end
$timescale
	1ps
$end
$scope module lab4_part1_TB $end
$var wire 1 ! Qout $end
$var wire 1 " Qnotout $end
$var reg 1 # Clkin $end
$var reg 1 $ Rin $end
$var reg 1 % Sin $end
$var reg 4 & count [3:0] $end
$scope module instantiate_gated_RS $end
$var wire 1 ! Q $end
$var wire 1 ' Qa $end
$var wire 1 ( Qb $end
$var wire 1 " Qnot $end
$var wire 1 $ R $end
$var wire 1 ) R_g $end
$var wire 1 % S $end
$var wire 1 * S_g $end
$var wire 1 # clk $end
$upscope $end
$upscope $end
$enddefinitions $end
$comment Show the parameter values. $end
$dumpall
$end
#0
$dumpvars
1*
1)
x(
x'
b0 &
0%
0$
0#
x"
x!
$end
#50000
b1 &
#100000
b10 &
#150000
b11 &
#200000
b100 &
1#
#250000
0!
0'
1"
1(
0)
1$
b101 &
#300000
1)
0$
b110 &
0#
#350000
b111 &
#400000
b1000 &
1#
#450000
0"
0(
1!
1'
0*
1%
b1001 &
#500000
1*
0%
b1010 &
0#
