Lab 2/P4/decoder_7seg.v
module decoder_7seg(code, decoded_output);

    input [1:0] code;
    output reg [6:0] decoded_output;

    always @(*) begin
        case (code)
            2'b00: decoded_output = 7'b0000111; // C(1:0) = 00
            2'b01: decoded_output = 7'b1110000; // C(1:0) = 01
            2'b10: decoded_output = 7'b0011100; // C(1:0) = 10
            2'b11: decoded_output = 7'b1100011; // C(1:0) = 11
            default: decoded_output = 7'b0000000; // Default case
        endcase
    end

endmodule

Lab 2/P6/two_bit_4to1muxV2.v
module two_bit_4to1muxV2 (s,u,v,w,x,m);
 
	input[1:0] s;
	input[1:0] u,v,w,x;
	output reg[1:0] m;
	
	reg[1:0] t1, t2;
	
	//complete always blocks (look at one_bit_4to1muxV2.v for hints. Should look the same)
	always @(u,v,s[0]) begin
		if (s[0] == 1'b0) begin
			t1 = u;
			t2 = w;
		end else begin
			t1 = v;
			t2 = x;
		end
	end
 
	always @(t1,t2,s[1]) begin
		if (s[1] == 1'b0)
			m = t1;
		else
			m = t2;
	end
endmodule

Lab 2/P6/part5.v
module part5 (s,u,v,w,x,chosen_7segCode);
 
	input[1:0] s;
	input[1:0] u, v, w, x;
	output[6:0] chosen_7segCode;
	
	wire[1:0] temp;
	
	/* need to connect an instance of two_bit_4to1mux or
	two_bit_4to1muxV2 (named part3) to an instance of decoder_7seg
	named part4. 
	
	Use the wire 2-bit called temp to connect them 
	(note output of two_bit_4to1mux is 2-bit, input to decoder_7seg is 
	2-bit)
	*/
	
	// Complete your choice of the following
	two_bit_4to1muxV2 part3(.s(s),.u(u),.v(v),.w(w),.x(x),.m(temp));
	decoder_7seg part4(.code(temp),.decoded_output(chosen_7segCode));

endmodule

Lab 2/P5/part5_TB.v
`timescale 1ns / 1ps
 
module part5_TB;
 
	// ------------------ Instantiate module ------------------
	// We are instantiating the module mux2, naming it instantiate_mux2.
	// select, input1, input2 are controlled by the testbench, output is 
	// checked  within the testbench
 
	reg [3:0] count;
	reg [1:0] S,U,V,W,X;
	
	wire [6:0] output_7seg;
	part5 instantiate_p5 (.s(S),.u(U),.v(V),.w(W),
								.x(X),.chosen_7segCode(output_7seg));
 	
	initial begin 
		count = 4'b0000;
	end
	
	always begin
		#50
		count=count+4'b0001;
	end
	
	always @(count) begin
		case (count)
		4'b0000 : begin S = 2'b00; U = 2'b00; V = 2'b01; W = 2'b10; X = 2'b11; end
		4'b0001 : begin S = 2'b00; U = 2'b01; V = 2'b10; W = 2'b11; X = 2'b00; end
		4'b0010 : begin S = 2'b01; U = 2'b10; V = 2'b11; W = 2'b00; X = 2'b01; end
		4'b0011 : begin S = 2'b10; U = 2'b11; V = 2'b00; W = 2'b01; X = 2'b10; end
		4'b0100 : begin S = 2'b11; U = 2'b00; V = 2'b01; W = 2'b10; X = 2'b11; end
		default : begin S = 2'b00; U = 2'b00; V = 2'b00; W = 2'b00; X = 2'b00; end
	endcase
	end


       // Terminate the simulation after a certain period
    initial begin
        // Initialize VCD dump
        $dumpfile("testbench.vcd");
        $dumpvars(0, part5_TB);
        
        #500 $finish;
    end
 
endmodule

Lab 2/P5/testbench.vcd
$date
	Thu Mar 27 14:19:12 2025
$end
$version
	Icarus Verilog
$end
$timescale
	1ps
$end
$scope module part5_TB $end
$var wire 7 ! output_7seg [6:0] $end
$var reg 2 " S [1:0] $end
$var reg 2 # U [1:0] $end
$var reg 2 $ V [1:0] $end
$var reg 2 % W [1:0] $end
$var reg 2 & X [1:0] $end
$var reg 4 ' count [3:0] $end
$scope module instantiate_p5 $end
$var wire 2 ( s [1:0] $end
$var wire 2 ) u [1:0] $end
$var wire 2 * v [1:0] $end
$var wire 2 + w [1:0] $end
$var wire 2 , x [1:0] $end
$var wire 2 - temp [1:0] $end
$var wire 7 . chosen_7segCode [6:0] $end
$scope module part3 $end
$var wire 2 / s [1:0] $end
$var wire 2 0 u [1:0] $end
$var wire 2 1 v [1:0] $end
$var wire 2 2 w [1:0] $end
$var wire 2 3 x [1:0] $end
$var reg 2 4 m [1:0] $end
$var reg 2 5 t1 [1:0] $end
$var reg 2 6 t2 [1:0] $end
$upscope $end
$scope module part4 $end
$var wire 2 7 code [1:0] $end
$var reg 7 8 decoded_output [6:0] $end
$upscope $end
$upscope $end
$upscope $end
$enddefinitions $end
$comment Show the parameter values. $end
$dumpall
$end
#0
$dumpvars
b111 8
b0 7
b10 6
b0 5
b0 4
b11 3
b10 2
b1 1
b0 0
b0 /
b111 .
b0 -
b11 ,
b10 +
b1 *
b0 )
b0 (
b0 '
b11 &
b10 %
b1 $
b0 #
b0 "
b111 !
$end
#50000
b1110000 !
b1110000 .
b1110000 8
b1 -
b1 4
b1 7
b11 6
b1 5
b0 &
b0 ,
b0 3
b11 %
b11 +
b11 2
b10 $
b10 *
b10 1
b1 #
b1 )
b1 0
b1 '
#100000
b1100011 !
b1100011 .
b1100011 8
b11 -
b11 4
b11 7
b1 6
b11 5
b1 &
b1 ,
b1 3
b0 %
b0 +
b0 2
b11 $
b11 *
b11 1
b10 #
b10 )
b10 0
b1 "
b1 (
b1 /
b10 '
#150000
b1110000 !
b1110000 .
b1110000 8
b1 -
b1 4
b1 7
b10 &
b10 ,
b10 3
b1 %
b1 +
b1 2
b0 $
b0 *
b0 1
b11 #
b11 )
b11 0
b10 "
b10 (
b10 /
b11 '
#200000
b1100011 !
b1100011 .
b1100011 8
b11 -
b11 4
b11 7
b11 6
b1 5
b11 &
b11 ,
b11 3
b10 %
b10 +
b10 2
b1 $
b1 *
b1 1
b0 #
b0 )
b0 0
b11 "
b11 (
b11 /
b100 '
#250000
b111 !
b111 .
b111 8
b0 -
b0 4
b0 7
b0 6
b0 5
b0 &
b0 ,
b0 3
b0 %
b0 +
b0 2
b0 $
b0 *
b0 1
b0 "
b0 (
b0 /
b101 '
#300000
b110 '
#350000
b111 '
#400000
b1000 '
#450000
b1001 '
#500000
b1010 '
